smart/tests/examples/cocotb/suv/suv.sv
`timescale 1ns / 1ps
module fixed_relu #(
    parameter IN_WIDTH = 8,
    /* verilator lint_off UNUSEDPARAM */
    parameter IN_FRAC_WIDTH = 0,
    parameter OUT_WIDTH = 8,
    parameter OUT_FRAC_WIDTH = 0,
    parameter OUT_SIZE = 0,
    /* verilator lint_on UNUSEDPARAM */
    parameter IN_SIZE = 8
) (
    /* verilator lint_off UNUSEDSIGNAL */
    input rst,
    input clk,
    /* verilator lint_on UNUSEDSIGNAL */
    input logic [IN_WIDTH-1:0] data_in[IN_SIZE-1:0],
    output logic [IN_WIDTH-1:0] data_out[IN_SIZE-1:0],

    input  logic data_in_valid,
    output logic data_in_ready,
    output logic data_out_valid,
    input  logic data_out_ready
);

  for (genvar i = 0; i < IN_SIZE; i++) begin : ReLU
    always_comb begin
      // negative value, put to zero
      if ($signed(data_in[i]) <= 0) data_out[i] = '0;
      else data_out[i] = data_in[i];
    end
  end

  assign data_out_valid = data_in_valid;
  assign data_in_ready  = data_out_ready;

endmodule

examples/cocotb/suv/sim_build/dump.vcd
$version Generated by VerilatedVcd $end
$timescale 1ps $end
 $scope module  $end
  $var wire 1 # rst $end
  $var wire 1 $ clk $end
  $var wire 32 % data_in[0] [31:0] $end
  $var wire 32 & data_in[1] [31:0] $end
  $var wire 32 ' data_in[2] [31:0] $end
  $var wire 32 ( data_in[3] [31:0] $end
  $var wire 32 ) data_in[4] [31:0] $end
  $var wire 32 * data_in[5] [31:0] $end
  $var wire 32 + data_in[6] [31:0] $end
  $var wire 32 , data_in[7] [31:0] $end
  $var wire 32 - data_in[8] [31:0] $end
  $var wire 32 . data_in[9] [31:0] $end
  $var wire 32 / data_in[10] [31:0] $end
  $var wire 32 0 data_in[11] [31:0] $end
  $var wire 32 1 data_in[12] [31:0] $end
  $var wire 32 2 data_in[13] [31:0] $end
  $var wire 32 3 data_in[14] [31:0] $end
  $var wire 32 4 data_in[15] [31:0] $end
  $var wire 32 5 data_out[0] [31:0] $end
  $var wire 32 6 data_out[1] [31:0] $end
  $var wire 32 7 data_out[2] [31:0] $end
  $var wire 32 8 data_out[3] [31:0] $end
  $var wire 32 9 data_out[4] [31:0] $end
  $var wire 32 : data_out[5] [31:0] $end
  $var wire 32 ; data_out[6] [31:0] $end
  $var wire 32 < data_out[7] [31:0] $end
  $var wire 32 = data_out[8] [31:0] $end
  $var wire 32 > data_out[9] [31:0] $end
  $var wire 32 ? data_out[10] [31:0] $end
  $var wire 32 @ data_out[11] [31:0] $end
  $var wire 32 A data_out[12] [31:0] $end
  $var wire 32 B data_out[13] [31:0] $end
  $var wire 32 C data_out[14] [31:0] $end
  $var wire 32 D data_out[15] [31:0] $end
  $var wire 1 E data_in_valid $end
  $var wire 1 F data_in_ready $end
  $var wire 1 G data_out_valid $end
  $var wire 1 H data_out_ready $end
  $scope module fixed_relu $end
   $var wire 32 o IN_WIDTH [31:0] $end
   $var wire 32 p IN_FRAC_WIDTH [31:0] $end
   $var wire 32 q OUT_WIDTH [31:0] $end
   $var wire 32 p OUT_FRAC_WIDTH [31:0] $end
   $var wire 32 p OUT_SIZE [31:0] $end
   $var wire 32 r IN_SIZE [31:0] $end
   $var wire 1 I rst $end
   $var wire 1 J clk $end
   $var wire 32 K data_in[0] [31:0] $end
   $var wire 32 L data_in[1] [31:0] $end
   $var wire 32 M data_in[2] [31:0] $end
   $var wire 32 N data_in[3] [31:0] $end
   $var wire 32 O data_in[4] [31:0] $end
   $var wire 32 P data_in[5] [31:0] $end
   $var wire 32 Q data_in[6] [31:0] $end
   $var wire 32 R data_in[7] [31:0] $end
   $var wire 32 S data_in[8] [31:0] $end
   $var wire 32 T data_in[9] [31:0] $end
   $var wire 32 U data_in[10] [31:0] $end
   $var wire 32 V data_in[11] [31:0] $end
   $var wire 32 W data_in[12] [31:0] $end
   $var wire 32 X data_in[13] [31:0] $end
   $var wire 32 Y data_in[14] [31:0] $end
   $var wire 32 Z data_in[15] [31:0] $end
   $var wire 32 [ data_out[0] [31:0] $end
   $var wire 32 \ data_out[1] [31:0] $end
   $var wire 32 ] data_out[2] [31:0] $end
   $var wire 32 ^ data_out[3] [31:0] $end
   $var wire 32 _ data_out[4] [31:0] $end
   $var wire 32 ` data_out[5] [31:0] $end
   $var wire 32 a data_out[6] [31:0] $end
   $var wire 32 b data_out[7] [31:0] $end
   $var wire 32 c data_out[8] [31:0] $end
   $var wire 32 d data_out[9] [31:0] $end
   $var wire 32 e data_out[10] [31:0] $end
   $var wire 32 f data_out[11] [31:0] $end
   $var wire 32 g data_out[12] [31:0] $end
   $var wire 32 h data_out[13] [31:0] $end
   $var wire 32 i data_out[14] [31:0] $end
   $var wire 32 j data_out[15] [31:0] $end
   $var wire 1 k data_in_valid $end
   $var wire 1 l data_in_ready $end
   $var wire 1 m data_out_valid $end
   $var wire 1 n data_out_ready $end
  $upscope $end
 $upscope $end
$enddefinitions $end


#0
0#
0$
b11111111111111111111111111110001 %
b11111111111111111111111111101001 &
b00000000000000000000000000110110 '
b11111111111111111111111111111101 (
b00000000000000000000000000111100 )
b11111111111111111111111111001010 *
b11111111111111111111111111101010 +
b00000000000000000000000000010010 ,
b00000000000000000000000000111111 -
b00000000000000000000000000111001 .
b11111111111111111111111111001110 /
b11111111111111111111111111001100 0
b00000000000000000000000000011001 1
b00000000000000000000000000110111 2
b00000000000000000000000000001101 3
b11111111111111111111111111111001 4
b00000000000000000000000000000000 5
b00000000000000000000000000000000 6
b00000000000000000000000000110110 7
b00000000000000000000000000000000 8
b00000000000000000000000000111100 9
b00000000000000000000000000000000 :
b00000000000000000000000000000000 ;
b00000000000000000000000000010010 <
b00000000000000000000000000111111 =
b00000000000000000000000000111001 >
b00000000000000000000000000000000 ?
b00000000000000000000000000000000 @
b00000000000000000000000000011001 A
b00000000000000000000000000110111 B
b00000000000000000000000000001101 C
b00000000000000000000000000000000 D
0E
0F
0G
0H
0I
0J
b11111111111111111111111111110001 K
b11111111111111111111111111101001 L
b00000000000000000000000000110110 M
b11111111111111111111111111111101 N
b00000000000000000000000000111100 O
b11111111111111111111111111001010 P
b11111111111111111111111111101010 Q
b00000000000000000000000000010010 R
b00000000000000000000000000111111 S
b00000000000000000000000000111001 T
b11111111111111111111111111001110 U
b11111111111111111111111111001100 V
b00000000000000000000000000011001 W
b00000000000000000000000000110111 X
b00000000000000000000000000001101 Y
b11111111111111111111111111111001 Z
b00000000000000000000000000000000 [
b00000000000000000000000000000000 \
b00000000000000000000000000110110 ]
b00000000000000000000000000000000 ^
b00000000000000000000000000111100 _
b00000000000000000000000000000000 `
b00000000000000000000000000000000 a
b00000000000000000000000000010010 b
b00000000000000000000000000111111 c
b00000000000000000000000000111001 d
b00000000000000000000000000000000 e
b00000000000000000000000000000000 f
b00000000000000000000000000011001 g
b00000000000000000000000000110111 h
b00000000000000000000000000001101 i
b00000000000000000000000000000000 j
0k
0l
0m
0n
b00000000000000000000000000100000 o
b00000000000000000000000000000000 p
b00000000000000000000000000001000 q
b00000000000000000000000000010000 r
#2000
b11111111111111111111111111000010 %
b11111111111111111111111111011101 &
b11111111111111111111111111111001 '
b11111111111111111111111111011000 (
b00000000000000000000000000001001 )
b11111111111111111111111111000011 *
b00000000000000000000000000011001 +
b11111111111111111111111111010101 ,
b11111111111111111111111111111001 -
b00000000000000000000000000000110 .
b11111111111111111111111111000010 /
b11111111111111111111111111111011 0
b11111111111111111111111111000000 1
b11111111111111111111111111000010 2
b11111111111111111111111111111110 3
b11111111111111111111111111100011 4
b00000000000000000000000000000000 7
b00000000000000000000000000001001 9
b00000000000000000000000000011001 ;
b00000000000000000000000000000000 <
b00000000000000000000000000000000 =
b00000000000000000000000000000110 >
b00000000000000000000000000000000 A
b00000000000000000000000000000000 B
b00000000000000000000000000000000 C
b11111111111111111111111111000010 K
b11111111111111111111111111011101 L
b11111111111111111111111111111001 M
b11111111111111111111111111011000 N
b00000000000000000000000000001001 O
b11111111111111111111111111000011 P
b00000000000000000000000000011001 Q
b11111111111111111111111111010101 R
b11111111111111111111111111111001 S
b00000000000000000000000000000110 T
b11111111111111111111111111000010 U
b11111111111111111111111111111011 V
b11111111111111111111111111000000 W
b11111111111111111111111111000010 X
b11111111111111111111111111111110 Y
b11111111111111111111111111100011 Z
b00000000000000000000000000000000 ]
b00000000000000000000000000001001 _
b00000000000000000000000000011001 a
b00000000000000000000000000000000 b
b00000000000000000000000000000000 c
b00000000000000000000000000000110 d
b00000000000000000000000000000000 g
b00000000000000000000000000000000 h
b00000000000000000000000000000000 i
#4000
b00000000000000000000000000011010 %
b11111111111111111111111111011110 &
b00000000000000000000000000001011 '
b11111111111111111111111111100010 (
b11111111111111111111111111001101 )
b11111111111111111111111111111011 *
b11111111111111111111111111001011 +
b00000000000000000000000000001000 ,
b00000000000000000000000000011110 -
b11111111111111111111111111111010 .
b00000000000000000000000000101010 /
b11111111111111111111111111101111 0
b00000000000000000000000000101100 1
b00000000000000000000000000001111 2
b11111111111111111111111111100000 3
b00000000000000000000000000011011 4
b00000000000000000000000000011010 5
b00000000000000000000000000001011 7
b00000000000000000000000000000000 9
b00000000000000000000000000000000 ;
b00000000000000000000000000001000 <
b00000000000000000000000000011110 =
b00000000000000000000000000000000 >
b00000000000000000000000000101010 ?
b00000000000000000000000000101100 A
b00000000000000000000000000001111 B
b00000000000000000000000000011011 D
b00000000000000000000000000011010 K
b11111111111111111111111111011110 L
b00000000000000000000000000001011 M
b11111111111111111111111111100010 N
b11111111111111111111111111001101 O
b11111111111111111111111111111011 P
b11111111111111111111111111001011 Q
b00000000000000000000000000001000 R
b00000000000000000000000000011110 S
b11111111111111111111111111111010 T
b00000000000000000000000000101010 U
b11111111111111111111111111101111 V
b00000000000000000000000000101100 W
b00000000000000000000000000001111 X
b11111111111111111111111111100000 Y
b00000000000000000000000000011011 Z
b00000000000000000000000000011010 [
b00000000000000000000000000001011 ]
b00000000000000000000000000000000 _
b00000000000000000000000000000000 a
b00000000000000000000000000001000 b
b00000000000000000000000000011110 c
b00000000000000000000000000000000 d
b00000000000000000000000000101010 e
b00000000000000000000000000101100 g
b00000000000000000000000000001111 h
b00000000000000000000000000011011 j
#6000
b00000000000000000000000000110000 %
b00000000000000000000000000000100 &
b00000000000000000000000000101100 '
b11111111111111111111111111010000 (
b00000000000000000000000000100101 )
b00000000000000000000000000100011 *
b11111111111111111111111111011001 +
b11111111111111111111111111101001 ,
b11111111111111111111111111100010 -
b00000000000000000000000000101101 .
b00000000000000000000000000010111 /
b00000000000000000000000000001010 0
b00000000000000000000000000111110 1
b00000000000000000000000000010100 2
b00000000000000000000000000111111 3
b11111111111111111111111111100000 4
b00000000000000000000000000110000 5
b00000000000000000000000000000100 6
b00000000000000000000000000101100 7
b00000000000000000000000000100101 9
b00000000000000000000000000100011 :
b00000000000000000000000000000000 <
b00000000000000000000000000000000 =
b00000000000000000000000000101101 >
b00000000000000000000000000010111 ?
b00000000000000000000000000001010 @
b00000000000000000000000000111110 A
b00000000000000000000000000010100 B
b00000000000000000000000000111111 C
b00000000000000000000000000000000 D
b00000000000000000000000000110000 K
b00000000000000000000000000000100 L
b00000000000000000000000000101100 M
b11111111111111111111111111010000 N
b00000000000000000000000000100101 O
b00000000000000000000000000100011 P
b11111111111111111111111111011001 Q
b11111111111111111111111111101001 R
b11111111111111111111111111100010 S
b00000000000000000000000000101101 T
b00000000000000000000000000010111 U
b00000000000000000000000000001010 V
b00000000000000000000000000111110 W
b00000000000000000000000000010100 X
b00000000000000000000000000111111 Y
b11111111111111111111111111100000 Z
b00000000000000000000000000110000 [
b00000000000000000000000000000100 \
b00000000000000000000000000101100 ]
b00000000000000000000000000100101 _
b00000000000000000000000000100011 `
b00000000000000000000000000000000 b
b00000000000000000000000000000000 c
b00000000000000000000000000101101 d
b00000000000000000000000000010111 e
b00000000000000000000000000001010 f
b00000000000000000000000000111110 g
b00000000000000000000000000010100 h
b00000000000000000000000000111111 i
b00000000000000000000000000000000 j
#8000
b00000000000000000000000000000101 %
b11111111111111111111111111000011 &
b11111111111111111111111111110111 '
b11111111111111111111111111101101 (
b11111111111111111111111111010101 )
b11111111111111111111111111010111 *
b11111111111111111111111111000100 +
b11111111111111111111111111101111 ,
b11111111111111111111111111111000 -
b00000000000000000000000000111100 /
b11111111111111111111111111010100 0
b11111111111111111111111111111001 1
b11111111111111111111111111111000 2
b00000000000000000000000000111100 3
b00000000000000000000000000011101 4
b00000000000000000000000000000101 5
b00000000000000000000000000000000 6
b00000000000000000000000000000000 7
b00000000000000000000000000000000 9
b00000000000000000000000000000000 :
b00000000000000000000000000111100 ?
b00000000000000000000000000000000 @
b00000000000000000000000000000000 A
b00000000000000000000000000000000 B
b00000000000000000000000000111100 C
b00000000000000000000000000011101 D
b00000000000000000000000000000101 K
b11111111111111111111111111000011 L
b11111111111111111111111111110111 M
b11111111111111111111111111101101 N
b11111111111111111111111111010101 O
b11111111111111111111111111010111 P
b11111111111111111111111111000100 Q
b11111111111111111111111111101111 R
b11111111111111111111111111111000 S
b00000000000000000000000000111100 U
b11111111111111111111111111010100 V
b11111111111111111111111111111001 W
b11111111111111111111111111111000 X
b00000000000000000000000000111100 Y
b00000000000000000000000000011101 Z
b00000000000000000000000000000101 [
b00000000000000000000000000000000 \
b00000000000000000000000000000000 ]
b00000000000000000000000000000000 _
b00000000000000000000000000000000 `
b00000000000000000000000000111100 e
b00000000000000000000000000000000 f
b00000000000000000000000000000000 g
b00000000000000000000000000000000 h
b00000000000000000000000000111100 i
b00000000000000000000000000011101 j
#10000
b11111111111111111111111111000011 %
b11111111111111111111111111010101 &
b00000000000000000000000000101001 '
b11111111111111111111111111110110 (
b11111111111111111111111111001011 )
b11111111111111111111111111011011 *
b00000000000000000000000000000000 +
b00000000000000000000000000001011 ,
b11111111111111111111111111000000 -
b11111111111111111111111111100000 .
b11111111111111111111111111000111 /
b11111111111111111111111111100010 0
b11111111111111111111111111010110 1
b00000000000000000000000000011111 2
b00000000000000000000000000010011 3
b00000000000000000000000000111101 4
b00000000000000000000000000000000 5
b00000000000000000000000000101001 7
b00000000000000000000000000001011 <
b00000000000000000000000000000000 >
b00000000000000000000000000000000 ?
b00000000000000000000000000011111 B
b00000000000000000000000000010011 C
b00000000000000000000000000111101 D
b11111111111111111111111111000011 K
b11111111111111111111111111010101 L
b00000000000000000000000000101001 M
b11111111111111111111111111110110 N
b11111111111111111111111111001011 O
b11111111111111111111111111011011 P
b00000000000000000000000000000000 Q
b00000000000000000000000000001011 R
b11111111111111111111111111000000 S
b11111111111111111111111111100000 T
b11111111111111111111111111000111 U
b11111111111111111111111111100010 V
b11111111111111111111111111010110 W
b00000000000000000000000000011111 X
b00000000000000000000000000010011 Y
b00000000000000000000000000111101 Z
b00000000000000000000000000000000 [
b00000000000000000000000000101001 ]
b00000000000000000000000000001011 b
b00000000000000000000000000000000 d
b00000000000000000000000000000000 e
b00000000000000000000000000011111 h
b00000000000000000000000000010011 i
b00000000000000000000000000111101 j
#12000
b11111111111111111111111111111010 %
b11111111111111111111111111101110 &
b11111111111111111111111111000001 '
b11111111111111111111111111101010 (
b00000000000000000000000000001101 )
b11111111111111111111111111011111 *
b00000000000000000000000000010010 +
b00000000000000000000000000010000 ,
b11111111111111111111111111111011 -
b11111111111111111111111111111111 .
b11111111111111111111111111111000 /
b11111111111111111111111111011011 0
b00000000000000000000000000011001 1
b00000000000000000000000000010100 2
b00000000000000000000000000110011 3
b00000000000000000000000000100000 4
b00000000000000000000000000000000 7
b00000000000000000000000000001101 9
b00000000000000000000000000010010 ;
b00000000000000000000000000010000 <
b00000000000000000000000000011001 A
b00000000000000000000000000010100 B
b00000000000000000000000000110011 C
b00000000000000000000000000100000 D
b11111111111111111111111111111010 K
b11111111111111111111111111101110 L
b11111111111111111111111111000001 M
b11111111111111111111111111101010 N
b00000000000000000000000000001101 O
b11111111111111111111111111011111 P
b00000000000000000000000000010010 Q
b00000000000000000000000000010000 R
b11111111111111111111111111111011 S
b11111111111111111111111111111111 T
b11111111111111111111111111111000 U
b11111111111111111111111111011011 V
b00000000000000000000000000011001 W
b00000000000000000000000000010100 X
b00000000000000000000000000110011 Y
b00000000000000000000000000100000 Z
b00000000000000000000000000000000 ]
b00000000000000000000000000001101 _
b00000000000000000000000000010010 a
b00000000000000000000000000010000 b
b00000000000000000000000000011001 g
b00000000000000000000000000010100 h
b00000000000000000000000000110011 i
b00000000000000000000000000100000 j
#14000
b00000000000000000000000000100001 %
b00000000000000000000000000100011 &
b00000000000000000000000000110100 '
b11111111111111111111111111010011 (
b11111111111111111111111111011111 )
b11111111111111111111111111010111 *
b00000000000000000000000000101001 +
b11111111111111111111111111011010 ,
b11111111111111111111111111001000 -
b00000000000000000000000000001110 .
b11111111111111111111111111100011 /
b11111111111111111111111111101001 0
b11111111111111111111111111110000 1
b11111111111111111111111111010110 2
b11111111111111111111111111011100 3
b00000000000000000000000000101010 4
b00000000000000000000000000100001 5
b00000000000000000000000000100011 6
b00000000000000000000000000110100 7
b00000000000000000000000000000000 9
b00000000000000000000000000101001 ;
b00000000000000000000000000000000 <
b00000000000000000000000000001110 >
b00000000000000000000000000000000 A
b00000000000000000000000000000000 B
b00000000000000000000000000000000 C
b00000000000000000000000000101010 D
b00000000000000000000000000100001 K
b00000000000000000000000000100011 L
b00000000000000000000000000110100 M
b11111111111111111111111111010011 N
b11111111111111111111111111011111 O
b11111111111111111111111111010111 P
b00000000000000000000000000101001 Q
b11111111111111111111111111011010 R
b11111111111111111111111111001000 S
b00000000000000000000000000001110 T
b11111111111111111111111111100011 U
b11111111111111111111111111101001 V
b11111111111111111111111111110000 W
b11111111111111111111111111010110 X
b11111111111111111111111111011100 Y
b00000000000000000000000000101010 Z
b00000000000000000000000000100001 [
b00000000000000000000000000100011 \
b00000000000000000000000000110100 ]
b00000000000000000000000000000000 _
b00000000000000000000000000101001 a
b00000000000000000000000000000000 b
b00000000000000000000000000001110 d
b00000000000000000000000000000000 g
b00000000000000000000000000000000 h
b00000000000000000000000000000000 i
b00000000000000000000000000101010 j
#16000
b11111111111111111111111111111010 %
b11111111111111111111111111001010 &
b00000000000000000000000000111010 '
b00000000000000000000000000011010 (
b11111111111111111111111111000011 )
b00000000000000000000000000110110 *
b11111111111111111111111111101011 +
b00000000000000000000000000010100 ,
b11111111111111111111111111101111 -
b11111111111111111111111111100100 .
b00000000000000000000000000000000 /
b00000000000000000000000000110111 0
b00000000000000000000000000010010 1
b11111111111111111111111111110011 2
b00000000000000000000000000110000 3
b00000000000000000000000000001001 4
b00000000000000000000000000000000 5
b00000000000000000000000000000000 6
b00000000000000000000000000111010 7
b00000000000000000000000000011010 8
b00000000000000000000000000110110 :
b00000000000000000000000000000000 ;
b00000000000000000000000000010100 <
b00000000000000000000000000000000 >
b00000000000000000000000000110111 @
b00000000000000000000000000010010 A
b00000000000000000000000000110000 C
b00000000000000000000000000001001 D
b11111111111111111111111111111010 K
b11111111111111111111111111001010 L
b00000000000000000000000000111010 M
b00000000000000000000000000011010 N
b11111111111111111111111111000011 O
b00000000000000000000000000110110 P
b11111111111111111111111111101011 Q
b00000000000000000000000000010100 R
b11111111111111111111111111101111 S
b11111111111111111111111111100100 T
b00000000000000000000000000000000 U
b00000000000000000000000000110111 V
b00000000000000000000000000010010 W
b11111111111111111111111111110011 X
b00000000000000000000000000110000 Y
b00000000000000000000000000001001 Z
b00000000000000000000000000000000 [
b00000000000000000000000000000000 \
b00000000000000000000000000111010 ]
b00000000000000000000000000011010 ^
b00000000000000000000000000110110 `
b00000000000000000000000000000000 a
b00000000000000000000000000010100 b
b00000000000000000000000000000000 d
b00000000000000000000000000110111 f
b00000000000000000000000000010010 g
b00000000000000000000000000110000 i
b00000000000000000000000000001001 j
#18000
b00000000000000000000000000001101 %
b00000000000000000000000000100001 &
b11111111111111111111111111110000 '
b11111111111111111111111111111111 (
b00000000000000000000000000100101 )
b11111111111111111111111111111011 *
b11111111111111111111111111111011 +
b00000000000000000000000000110101 ,
b11111111111111111111111111010111 -
b11111111111111111111111111010110 .
b00000000000000000000000000101001 /
b11111111111111111111111111000010 0
b00000000000000000000000000000001 1
b11111111111111111111111111011111 2
b11111111111111111111111111110101 3
b00000000000000000000000000000010 4
b00000000000000000000000000001101 5
b00000000000000000000000000100001 6
b00000000000000000000000000000000 7
b00000000000000000000000000000000 8
b00000000000000000000000000100101 9
b00000000000000000000000000000000 :
b00000000000000000000000000110101 <
b00000000000000000000000000101001 ?
b00000000000000000000000000000000 @
b00000000000000000000000000000001 A
b00000000000000000000000000000000 C
b00000000000000000000000000000010 D
b00000000000000000000000000001101 K
b00000000000000000000000000100001 L
b11111111111111111111111111110000 M
b11111111111111111111111111111111 N
b00000000000000000000000000100101 O
b11111111111111111111111111111011 P
b11111111111111111111111111111011 Q
b00000000000000000000000000110101 R
b11111111111111111111111111010111 S
b11111111111111111111111111010110 T
b00000000000000000000000000101001 U
b11111111111111111111111111000010 V
b00000000000000000000000000000001 W
b11111111111111111111111111011111 X
b11111111111111111111111111110101 Y
b00000000000000000000000000000010 Z
b00000000000000000000000000001101 [
b00000000000000000000000000100001 \
b00000000000000000000000000000000 ]
b00000000000000000000000000000000 ^
b00000000000000000000000000100101 _
b00000000000000000000000000000000 `
b00000000000000000000000000110101 b
b00000000000000000000000000101001 e
b00000000000000000000000000000000 f
b00000000000000000000000000000001 g
b00000000000000000000000000000000 i
b00000000000000000000000000000010 j
#20000
b11111111111111111111111111100001 %
b11111111111111111111111111100110 &
b11111111111111111111111111101010 '
b00000000000000000000000000111001 (
b00000000000000000000000000010101 )
b00000000000000000000000000001111 *
b11111111111111111111111111001111 +
b11111111111111111111111111100110 ,
b11111111111111111111111111001110 -
b00000000000000000000000000001110 .
b11111111111111111111111111100110 /
b11111111111111111111111111100110 0
b00000000000000000000000000010010 1
b11111111111111111111111111100010 2
b11111111111111111111111111001010 3
b00000000000000000000000000101001 4
b00000000000000000000000000000000 5
b00000000000000000000000000000000 6
b00000000000000000000000000111001 8
b00000000000000000000000000010101 9
b00000000000000000000000000001111 :
b00000000000000000000000000000000 <
b00000000000000000000000000001110 >
b00000000000000000000000000000000 ?
b00000000000000000000000000010010 A
b00000000000000000000000000101001 D
b11111111111111111111111111100001 K
b11111111111111111111111111100110 L
b11111111111111111111111111101010 M
b00000000000000000000000000111001 N
b00000000000000000000000000010101 O
b00000000000000000000000000001111 P
b11111111111111111111111111001111 Q
b11111111111111111111111111100110 R
b11111111111111111111111111001110 S
b00000000000000000000000000001110 T
b11111111111111111111111111100110 U
b11111111111111111111111111100110 V
b00000000000000000000000000010010 W
b11111111111111111111111111100010 X
b11111111111111111111111111001010 Y
b00000000000000000000000000101001 Z
b00000000000000000000000000000000 [
b00000000000000000000000000000000 \
b00000000000000000000000000111001 ^
b00000000000000000000000000010101 _
b00000000000000000000000000001111 `
b00000000000000000000000000000000 b
b00000000000000000000000000001110 d
b00000000000000000000000000000000 e
b00000000000000000000000000010010 g
b00000000000000000000000000101001 j
#22000
b00000000000000000000000000100011 %
b00000000000000000000000000011011 &
b11111111111111111111111111101011 '
b11111111111111111111111111011110 (
b00000000000000000000000000111010 )
b11111111111111111111111111100011 *
b00000000000000000000000000001001 +
b00000000000000000000000000010001 ,
b11111111111111111111111111000101 -
b00000000000000000000000000100011 .
b00000000000000000000000000110000 /
b11111111111111111111111111010011 0
b11111111111111111111111111111011 1
b11111111111111111111111111010110 2
b11111111111111111111111111101100 3
b11111111111111111111111111100101 4
b00000000000000000000000000100011 5
b00000000000000000000000000011011 6
b00000000000000000000000000000000 8
b00000000000000000000000000111010 9
b00000000000000000000000000000000 :
b00000000000000000000000000001001 ;
b00000000000000000000000000010001 <
b00000000000000000000000000100011 >
b00000000000000000000000000110000 ?
b00000000000000000000000000000000 A
b00000000000000000000000000000000 D
b00000000000000000000000000100011 K
b00000000000000000000000000011011 L
b11111111111111111111111111101011 M
b11111111111111111111111111011110 N
b00000000000000000000000000111010 O
b11111111111111111111111111100011 P
b00000000000000000000000000001001 Q
b00000000000000000000000000010001 R
b11111111111111111111111111000101 S
b00000000000000000000000000100011 T
b00000000000000000000000000110000 U
b11111111111111111111111111010011 V
b11111111111111111111111111111011 W
b11111111111111111111111111010110 X
b11111111111111111111111111101100 Y
b11111111111111111111111111100101 Z
b00000000000000000000000000100011 [
b00000000000000000000000000011011 \
b00000000000000000000000000000000 ^
b00000000000000000000000000111010 _
b00000000000000000000000000000000 `
b00000000000000000000000000001001 a
b00000000000000000000000000010001 b
b00000000000000000000000000100011 d
b00000000000000000000000000110000 e
b00000000000000000000000000000000 g
b00000000000000000000000000000000 j
#24000
b00000000000000000000000000010100 %
b00000000000000000000000000001100 &
b11111111111111111111111111110001 '
b00000000000000000000000000011111 (
b11111111111111111111111111111001 )
b11111111111111111111111111101011 *
b00000000000000000000000000110110 +
b00000000000000000000000000100100 ,
b11111111111111111111111111001011 -
b00000000000000000000000000011011 .
b00000000000000000000000000001011 /
b00000000000000000000000000010000 0
b00000000000000000000000000011000 1
b00000000000000000000000000111100 2
b00000000000000000000000000011100 3
b00000000000000000000000000111101 4
b00000000000000000000000000010100 5
b00000000000000000000000000001100 6
b00000000000000000000000000011111 8
b00000000000000000000000000000000 9
b00000000000000000000000000110110 ;
b00000000000000000000000000100100 <
b00000000000000000000000000011011 >
b00000000000000000000000000001011 ?
b00000000000000000000000000010000 @
b00000000000000000000000000011000 A
b00000000000000000000000000111100 B
b00000000000000000000000000011100 C
b00000000000000000000000000111101 D
b00000000000000000000000000010100 K
b00000000000000000000000000001100 L
b11111111111111111111111111110001 M
b00000000000000000000000000011111 N
b11111111111111111111111111111001 O
b11111111111111111111111111101011 P
b00000000000000000000000000110110 Q
b00000000000000000000000000100100 R
b11111111111111111111111111001011 S
b00000000000000000000000000011011 T
b00000000000000000000000000001011 U
b00000000000000000000000000010000 V
b00000000000000000000000000011000 W
b00000000000000000000000000111100 X
b00000000000000000000000000011100 Y
b00000000000000000000000000111101 Z
b00000000000000000000000000010100 [
b00000000000000000000000000001100 \
b00000000000000000000000000011111 ^
b00000000000000000000000000000000 _
b00000000000000000000000000110110 a
b00000000000000000000000000100100 b
b00000000000000000000000000011011 d
b00000000000000000000000000001011 e
b00000000000000000000000000010000 f
b00000000000000000000000000011000 g
b00000000000000000000000000111100 h
b00000000000000000000000000011100 i
b00000000000000000000000000111101 j
#26000
b00000000000000000000000000111111 %
b11111111111111111111111111100100 &
b00000000000000000000000000001101 '
b00000000000000000000000000000011 (
b11111111111111111111111111000110 )
b00000000000000000000000000111001 *
b00000000000000000000000000011010 +
b11111111111111111111111111100101 ,
b11111111111111111111111111010111 -
b00000000000000000000000000111011 .
b00000000000000000000000000101010 /
b00000000000000000000000000001000 0
b00000000000000000000000000101101 1
b11111111111111111111111111111010 2
b00000000000000000000000000010100 3
b00000000000000000000000000010101 4
b00000000000000000000000000111111 5
b00000000000000000000000000000000 6
b00000000000000000000000000001101 7
b00000000000000000000000000000011 8
b00000000000000000000000000111001 :
b00000000000000000000000000011010 ;
b00000000000000000000000000000000 <
b00000000000000000000000000111011 >
b00000000000000000000000000101010 ?
b00000000000000000000000000001000 @
b00000000000000000000000000101101 A
b00000000000000000000000000000000 B
b00000000000000000000000000010100 C
b00000000000000000000000000010101 D
b00000000000000000000000000111111 K
b11111111111111111111111111100100 L
b00000000000000000000000000001101 M
b00000000000000000000000000000011 N
b11111111111111111111111111000110 O
b00000000000000000000000000111001 P
b00000000000000000000000000011010 Q
b11111111111111111111111111100101 R
b11111111111111111111111111010111 S
b00000000000000000000000000111011 T
b00000000000000000000000000101010 U
b00000000000000000000000000001000 V
b00000000000000000000000000101101 W
b11111111111111111111111111111010 X
b00000000000000000000000000010100 Y
b00000000000000000000000000010101 Z
b00000000000000000000000000111111 [
b00000000000000000000000000000000 \
b00000000000000000000000000001101 ]
b00000000000000000000000000000011 ^
b00000000000000000000000000111001 `
b00000000000000000000000000011010 a
b00000000000000000000000000000000 b
b00000000000000000000000000111011 d
b00000000000000000000000000101010 e
b00000000000000000000000000001000 f
b00000000000000000000000000101101 g
b00000000000000000000000000000000 h
b00000000000000000000000000010100 i
b00000000000000000000000000010101 j
